Grindr/__init__.py
Grindr/client/__init__.py
Grindr/client/client.py
Grindr/client/emitter.py
Grindr/client/errors.py
Grindr/client/extension.py
Grindr/client/logger.py
Grindr/client/tls_match/__init__.py
Grindr/client/tls_match/ja3_blueprint.json
Grindr/client/tls_match/tls_match.py
Grindr/client/web/__init__.py
Grindr/client/web/web_base.py
Grindr/client/web/web_client.py
Grindr/client/web/web_settings.py
Grindr/client/web/routes/__init__.py
Grindr/client/web/routes/fetch/__init__.py
Grindr/client/web/routes/fetch/fetch_album.py
Grindr/client/web/routes/fetch/fetch_albums.py
Grindr/client/web/routes/fetch/fetch_albums_red_dot.py
Grindr/client/web/routes/fetch/fetch_assignments.py
Grindr/client/web/routes/fetch/fetch_blocks.py
Grindr/client/web/routes/fetch/fetch_boost_sessions.py
Grindr/client/web/routes/fetch/fetch_cascade.py
Grindr/client/web/routes/fetch/fetch_chat_media.py
Grindr/client/web/routes/fetch/fetch_eyeball.py
Grindr/client/web/routes/fetch/fetch_favorites.py
Grindr/client/web/routes/fetch/fetch_genders.py
Grindr/client/web/routes/fetch/fetch_google_play_products.py
Grindr/client/web/routes/fetch/fetch_inbox.py
Grindr/client/web/routes/fetch/fetch_legal_agreements.py
Grindr/client/web/routes/fetch/fetch_messages.py
Grindr/client/web/routes/fetch/fetch_my_profile.py
Grindr/client/web/routes/fetch/fetch_offers_eligible.py
Grindr/client/web/routes/fetch/fetch_opt_out.py
Grindr/client/web/routes/fetch/fetch_prefs.py
Grindr/client/web/routes/fetch/fetch_profile.py
Grindr/client/web/routes/fetch/fetch_profile_images.py
Grindr/client/web/routes/fetch/fetch_profile_tag_translations.py
Grindr/client/web/routes/fetch/fetch_profiles.py
Grindr/client/web/routes/fetch/fetch_rewarded_chats.py
Grindr/client/web/routes/fetch/fetch_session.py
Grindr/client/web/routes/fetch/fetch_shared_albums.py
Grindr/client/web/routes/fetch/fetch_tags.py
Grindr/client/web/routes/fetch/fetch_taps.py
Grindr/client/web/routes/fetch/fetch_taps_sent.py
Grindr-0.3.0.post9.dist-info/LICENSE
Grindr-0.3.0.post9.dist-info/METADATA
Grindr-0.3.0.post9.dist-info/WHEEL
Grindr-0.3.0.post9.dist-info/top_level.txt
Grindr-0.3.0.post9.dist-info/RECORD
