Metadata-Version: 2.2
Name: Grindr
Version: 0.3.0.post9
Summary: Grindr Python Client
Home-page: https://github.com/isaackogan/Grindr
Author: Tricorder
Author-email: tricorder@isaackogan.com
License: MIT
Keywords: Grindr,Grindr API,python3,api,unofficial
Classifier: Development Status :: 4 - Beta
Classifier: Intended Audience :: Developers
Classifier: Topic :: Software Development :: Build Tools
Classifier: License :: OSI Approved :: MIT License
Classifier: Natural Language :: English
Classifier: Programming Language :: Python :: 3.12
Classifier: Framework :: Pydantic :: 2
License-File: LICENSE
Requires-Dist: pyee==12.1.1
Requires-Dist: pygeohash==1.2.0
Requires-Dist: pydantic
Requires-Dist: curl_cffi==0.8.1b8
Dynamic: author
Dynamic: author-email
Dynamic: classifier
Dynamic: description
Dynamic: description-content-type
Dynamic: home-page
Dynamic: keywords
Dynamic: license
Dynamic: requires-dist
Dynamic: summary
